activitysmith/__init__.py
activitysmith/client.py
activitysmith-0.1.0.dist-info/licenses/LICENSE
activitysmith_openapi/__init__.py
activitysmith_openapi/api_client.py
activitysmith_openapi/api_response.py
activitysmith_openapi/configuration.py
activitysmith_openapi/exceptions.py
activitysmith_openapi/rest.py
activitysmith_openapi/api/__init__.py
activitysmith_openapi/api/live_activities_api.py
activitysmith_openapi/api/push_notifications_api.py
activitysmith_openapi/models/__init__.py
activitysmith_openapi/models/content_state_end.py
activitysmith_openapi/models/content_state_start.py
activitysmith_openapi/models/content_state_update.py
activitysmith_openapi/models/live_activity_end_request.py
activitysmith_openapi/models/live_activity_end_response.py
activitysmith_openapi/models/live_activity_limit_error.py
activitysmith_openapi/models/live_activity_start_request.py
activitysmith_openapi/models/live_activity_start_response.py
activitysmith_openapi/models/live_activity_update_request.py
activitysmith_openapi/models/live_activity_update_response.py
activitysmith_openapi/models/push_notification_request.py
activitysmith_openapi/models/push_notification_response.py
activitysmith_openapi/models/rate_limit_error.py
activitysmith_openapi/models/send_push_notification429_response.py
activitysmith_openapi/test/__init__.py
activitysmith_openapi/test/test_content_state_end.py
activitysmith_openapi/test/test_content_state_start.py
activitysmith_openapi/test/test_content_state_update.py
activitysmith_openapi/test/test_live_activities_api.py
activitysmith_openapi/test/test_live_activity_end_request.py
activitysmith_openapi/test/test_live_activity_end_response.py
activitysmith_openapi/test/test_live_activity_limit_error.py
activitysmith_openapi/test/test_live_activity_start_request.py
activitysmith_openapi/test/test_live_activity_start_response.py
activitysmith_openapi/test/test_live_activity_update_request.py
activitysmith_openapi/test/test_live_activity_update_response.py
activitysmith-0.1.0.dist-info/METADATA
activitysmith-0.1.0.dist-info/WHEEL
activitysmith-0.1.0.dist-info/top_level.txt
activitysmith-0.1.0.dist-info/RECORD
