Metadata-Version: 2.4
Name: activitysmith
Version: 0.1.0
Summary: Official ActivitySmith Python SDK
Author-email: ActivitySmith <adam@activitysmith.com>
License: MIT
Project-URL: homepage, https://activitysmith.com
Project-URL: documentation, https://activitysmith.com/docs
Project-URL: source, https://github.com/ActivitySmithHQ/activitysmith-python
Project-URL: issues, https://github.com/ActivitySmithHQ/activitysmith-python/issues
Keywords: activitysmith,live activities,push notifications,api,sdk
Requires-Python: >=3.9
License-File: LICENSE
Requires-Dist: urllib3>=1.25.3
Requires-Dist: python-dateutil>=2.8.2
Requires-Dist: pydantic>=2
Provides-Extra: dev
Requires-Dist: pytest>=7; extra == "dev"
Requires-Dist: ruff>=0.5; extra == "dev"
Dynamic: license-file
